module.v
module fir_16tap #
(
    parameter N = 16,             
    parameter COEFF_WIDTH = 16,    
    parameter DATA_WIDTH = 16      
)
(
    input  wire              clk,
    input  wire              rst,
    input  wire              enable,   // Clock gating 
    input  wire signed [DATA_WIDTH-1:0] x_in,   
    output reg  signed [DATA_WIDTH-1:0] y_out   
);

integer i;
localparam HALF_N = N/2;
localparam ACC_WIDTH = DATA_WIDTH + COEFF_WIDTH + $clog2(N);

//Input Register
reg signed [DATA_WIDTH-1:0] x_reg;

always @(posedge clk) begin
    if (rst)
        x_reg <= {DATA_WIDTH{1'b0}};
    else if (enable)
        x_reg <= x_in;
end

// Shift Register 
reg signed [DATA_WIDTH-1:0] x_shift [0:N-1];

always @(posedge clk) begin
    if (rst) begin
        for (i = 0; i < N; i = i + 1)
            x_shift[i] <= {DATA_WIDTH{1'b0}};
    end else if (enable) begin
        x_shift[0] <= x_reg;
        for (i = 1; i < N; i = i + 1)
            x_shift[i] <= x_shift[i-1];
    end
end


// Pre-adders 
reg signed [DATA_WIDTH:0] pre_add [0:HALF_N-1];  

always @(posedge clk) begin
    if (rst) begin
        for (i = 0; i < HALF_N; i = i + 1)
            pre_add[i] <= {(DATA_WIDTH+1){1'b0}};
    end else if (enable) begin
        for (i = 0; i < HALF_N; i = i + 1)
            pre_add[i] <= x_shift[i] + x_shift[N-1-i];
    end
end

// Bit Shifts 
localparam BASE_SHIFT = 6;  
reg signed [ACC_WIDTH-1:0] shift_out [0:HALF_N-1];

always @(posedge clk) begin
    if (rst) begin
        for (i = 0; i < HALF_N; i = i + 1)
            shift_out[i] <= {ACC_WIDTH{1'b0}};
    end else if (enable) begin
        for (i = 0; i < HALF_N; i = i + 1)
            shift_out[i] <= pre_add[i] <<< (BASE_SHIFT + i);
    end
end

// Parameterized Adder Tree using generate blocks

localparam NUM_STAGES = $clog2(HALF_N);  

reg signed [ACC_WIDTH-1:0] adder_tree [0:NUM_STAGES][0:HALF_N-1];

genvar stage, idx;
generate
    // First stage: connect to shift outputs
    for (idx = 0; idx < HALF_N; idx = idx + 1) begin : first_stage_assign
        always @(posedge clk) begin
            if (rst)
                adder_tree[0][idx] <= {ACC_WIDTH{1'b0}};
            else if (enable)
                adder_tree[0][idx] <= shift_out[idx];
        end
    end
    
    // Subsequent stages: binary tree addition
    for (stage = 1; stage <= NUM_STAGES; stage = stage + 1) begin : adder_stages
        localparam STAGE_SIZE = HALF_N >> stage;  // Number of adders in this stage
        for (idx = 0; idx < STAGE_SIZE; idx = idx + 1) begin : adder_level
            always @(posedge clk) begin
                if (rst)
                    adder_tree[stage][idx] <= {ACC_WIDTH{1'b0}};
                else if (enable)
                    adder_tree[stage][idx] <= adder_tree[stage-1][2*idx] + adder_tree[stage-1][2*idx+1];
            end
        end
    end
endgenerate

// Final accumulator from last stage
wire signed [ACC_WIDTH-1:0] acc;
assign acc = adder_tree[NUM_STAGES][0];

//Scaling & Saturation
localparam SCALE_SHIFT = COEFF_WIDTH - 1;  
localparam SCALED_WIDTH = ACC_WIDTH - SCALE_SHIFT + 1;
wire signed [SCALED_WIDTH-1:0] scaled;
assign scaled = (acc + (1 << (SCALE_SHIFT-1))) >>> SCALE_SHIFT;  

localparam MAX_POS = (1 << (DATA_WIDTH-1)) - 1;    // 32767 for 16-bit
localparam MAX_NEG = -(1 << (DATA_WIDTH-1));        // -32768 for 16-bit

always @(posedge clk) begin
    if (rst)
        y_out <= {DATA_WIDTH{1'b0}};
    else if (enable) begin
        if (scaled > MAX_POS)
            y_out <= MAX_POS[DATA_WIDTH-1:0];
        else if (scaled < MAX_NEG)
            y_out <= MAX_NEG[DATA_WIDTH-1:0];
        else
            y_out <= scaled[DATA_WIDTH-1:0];
    end
end

endmodule

testbench.v
`timescale 1ns/1ps

module tb_fir_16tap;

parameter N            = 16;
parameter DUT_LATENCY  = 9;    
parameter REF_DELAY    = 7;    

reg clk;
reg rst;
reg enable;
reg signed [15:0] x_in;
wire signed [15:0] y_out;

// VCD Dump 
initial begin
    $dumpfile("dump.vcd");
    $dumpvars(0, tb_fir_16tap);
end

//DUT 
fir_16tap dut (
    .clk(clk),
    .rst(rst),
    .enable(enable),
    .x_in(x_in),
    .y_out(y_out)
);

// Clock 
always #5 clk = ~clk;

//Coefficients - Symmetric pattern
reg signed [15:0] coeff [0:N-1];
initial begin
    coeff[0]=64;   coeff[1]=128;  coeff[2]=256;  coeff[3]=512;
    coeff[4]=1024; coeff[5]=2048; coeff[6]=4096; coeff[7]=8192;
    coeff[8]=8192; coeff[9]=4096; coeff[10]=2048; coeff[11]=1024;
    coeff[12]=512; coeff[13]=256; coeff[14]=128;  coeff[15]=64;
end

// Input Register with enable
reg signed [15:0] x_reg_ref;

always @(posedge clk) begin
    if (rst)
        x_reg_ref <= 0;
    else if (enable)
        x_reg_ref <= x_in;
end

// Shift Register 
reg signed [15:0] x_hist [0:N-1];
integer i;

always @(posedge clk) begin
    if (rst) begin
        for (i = 0; i < N; i = i + 1)
            x_hist[i] <= 0;
    end else if (enable) begin
        x_hist[0] <= x_reg_ref;
        for (i = 1; i < N; i = i + 1)
            x_hist[i] <= x_hist[i-1];
    end
end

// Pure Combinational FIR Reference 
reg signed [35:0] acc_ref;
reg signed [15:0] y_ref;

always @(*) begin
    acc_ref = 0;
    for (i = 0; i < N; i = i + 1)
        acc_ref = acc_ref + x_hist[i] * coeff[i];
end

always @(*) begin
    if (((acc_ref + 36'sd16384) >>> 15) > 32767)
        y_ref = 32767;
    else if (((acc_ref + 36'sd16384) >>> 15) < -32768)
        y_ref = -32768;
    else
        y_ref = (acc_ref + 36'sd16384) >>> 15;
end

// Output Pipeline 
reg signed [15:0] y_ref_pipe [0:REF_DELAY-1];

always @(posedge clk) begin
    if (rst) begin
        for (i = 0; i < REF_DELAY; i = i + 1)
            y_ref_pipe[i] <= 0;
    end else if (enable) begin
        y_ref_pipe[0] <= y_ref;
        for (i = 1; i < REF_DELAY; i = i + 1)
            y_ref_pipe[i] <= y_ref_pipe[i-1];
    end
end

// Performance Counters
reg [31:0] sample_count;
reg [31:0] mismatch_count;
reg [31:0] saturation_count;
reg [31:0] test_count;

initial begin
    sample_count = 0;
    mismatch_count = 0;
    saturation_count = 0;
    test_count = 0;
end

// Count samples processed
always @(posedge clk) begin
    if (!rst && enable)
        sample_count <= sample_count + 1;
end

// Count saturation events
wire signed [20:0] scaled_monitor;
assign scaled_monitor = ((acc_ref + 36'sd16384) >>> 15);

always @(posedge clk) begin
    if (!rst && (scaled_monitor > 32767 || scaled_monitor < -32768))
        saturation_count <= saturation_count + 1;
end

// Stimulus with enhanced tests
initial begin
    clk  = 0;
    rst  = 1;
    enable = 1;
    x_in = 0;

    #20 rst = 0;
    $display("\n========== FIR FILTER VERIFICATION ==========");
    
    // Test 1: Impulse Response
    $display("\n[TEST 1] Impulse Response Test");
    test_count = test_count + 1;
    @(posedge clk);
    x_in = 16'sd16384;   // 0.5 in Q1.15
    @(posedge clk);
    x_in = 0;
    repeat (20) @(posedge clk);
    
    // Test 2: Step Response
    $display("\n[TEST 2] Step Response Test");
    test_count = test_count + 1;
    repeat (30) begin
        @(posedge clk);
        x_in = 16'sd8192;  // Constant 0.25
    end
    @(posedge clk);
    x_in = 0;
    repeat (20) @(posedge clk);
    
    // Test 3: Edge Cases - Maximum Positive
    $display("\n[TEST 3] Edge Case - Maximum Positive Input");
    test_count = test_count + 1;
    repeat (20) begin
        @(posedge clk);
        x_in = 16'sd32767;  // Max positive
    end
    @(posedge clk);
    x_in = 0;
    repeat (20) @(posedge clk);
    
    // Test 4: Edge Cases - Maximum Negative
    $display("\n[TEST 4] Edge Case - Maximum Negative Input");
    test_count = test_count + 1;
    repeat (20) begin
        @(posedge clk);
        x_in = -16'sd32768;  // Max negative
    end
    @(posedge clk);
    x_in = 0;
    repeat (20) @(posedge clk);
    
    // Test 5: Alternating Pattern
    $display("\n[TEST 5] Alternating Pattern Test");
    test_count = test_count + 1;
    repeat (20) begin
        @(posedge clk);
        x_in = 16'sd16384;
        @(posedge clk);
        x_in = -16'sd16384;
    end
    @(posedge clk);
    x_in = 0;
    repeat (20) @(posedge clk);
    
    // Test 6: Random Input
    $display("\n[TEST 6] Random Input Test");
    test_count = test_count + 1;
    repeat (50) begin
        @(posedge clk);
        x_in = $random;
    end
    @(posedge clk);
    x_in = 0;
    repeat (20) @(posedge clk);
    
    // Test 7: Clock Gating Test
    $display("\n[TEST 7] Clock Gating Test");
    test_count = test_count + 1;
    @(posedge clk);
    x_in = 16'sd10000;
    @(posedge clk);
    enable = 0;  // Disable filter
    repeat (10) begin
        @(posedge clk);
        x_in = $random;  
    end
    enable = 1; 
    @(posedge clk);
    x_in = 0;
    repeat (20) @(posedge clk);
    
    // Test 8: Zero Input Stability
    $display("\n[TEST 8] Zero Input Stability Test");
    test_count = test_count + 1;
    repeat (30) begin
        @(posedge clk);
        x_in = 0;
    end
    
    
    #100;
    $display("\n========== TEST STATISTICS ==========");
    $display("Total Tests Run:       %0d", test_count);
    $display("Total Samples:         %0d", sample_count);
    $display("Mismatches:            %0d", mismatch_count);
    $display("Saturation Events:     %0d", saturation_count);
    if (mismatch_count == 0)
        $display("\n✅ ALL TESTS PASSED!");
    else
        $display("\n❌ TESTS FAILED - %0d mismatches detected", mismatch_count);
    $display("=========================================\n");
    
    #100 $finish;
end


reg [7:0] check_delay;

always @(posedge clk) begin
    if (rst)
        check_delay <= 0;
    else if (check_delay < DUT_LATENCY + 2)
        check_delay <= check_delay + 1;
end

// Enhanced verification with mismatch tracking
always @(posedge clk) begin
    if (!rst && check_delay >= DUT_LATENCY + 2) begin
        if (y_out !== y_ref_pipe[REF_DELAY-1]) begin
            mismatch_count <= mismatch_count + 1;
            $display("❌ MISMATCH @ %0t | DUT=%d REF=%d",
                     $time, y_out, y_ref_pipe[REF_DELAY-1]);
        end else if (enable) begin  
            $display("✅ OK @ %0t | y=%d", $time, y_out);
        end
    end
end

// Assertions for runtime checking
always @(posedge clk) begin
    if (!rst && enable) begin
        
        if (y_out > 16'sd32767 || y_out < -16'sd32768) begin
            $display("⚠️  WARNING @ %0t: Output out of range: %d", $time, y_out);
        end
    end
end

endmodule

dump.vcd
$date
	Tue Jan 27 00:09:14 2026
$end
$version
	Icarus Verilog
$end
$timescale
	1ps
$end
$scope module tb_fir_16tap $end
$var wire 16 ! y_out [15:0] $end
$var wire 21 " scaled_monitor [20:0] $end
$var parameter 32 # DUT_LATENCY $end
$var parameter 32 $ N $end
$var parameter 32 % REF_DELAY $end
$var reg 36 & acc_ref [35:0] $end
$var reg 8 ' check_delay [7:0] $end
$var reg 1 ( clk $end
$var reg 1 ) enable $end
$var reg 32 * mismatch_count [31:0] $end
$var reg 1 + rst $end
$var reg 32 , sample_count [31:0] $end
$var reg 32 - saturation_count [31:0] $end
$var reg 32 . test_count [31:0] $end
$var reg 16 / x_in [15:0] $end
$var reg 16 0 x_reg_ref [15:0] $end
$var reg 16 1 y_ref [15:0] $end
$var integer 32 2 i [31:0] $end
$scope module dut $end
$var wire 36 3 acc [35:0] $end
$var wire 1 ( clk $end
$var wire 1 ) enable $end
$var wire 1 + rst $end
$var wire 16 4 x_in [15:0] $end
$var wire 22 5 scaled [21:0] $end
$var parameter 34 6 ACC_WIDTH $end
$var parameter 32 7 BASE_SHIFT $end
$var parameter 32 8 COEFF_WIDTH $end
$var parameter 32 9 DATA_WIDTH $end
$var parameter 32 : HALF_N $end
$var parameter 47 ; MAX_NEG $end
$var parameter 48 < MAX_POS $end
$var parameter 32 = N $end
$var parameter 32 > NUM_STAGES $end
$var parameter 36 ? SCALED_WIDTH $end
$var parameter 33 @ SCALE_SHIFT $end
$var reg 16 A x_reg [15:0] $end
$var reg 16 B y_out [15:0] $end
$var integer 32 C i [31:0] $end
$scope begin adder_stages[1] $end
$var parameter 32 D STAGE_SIZE $end
$var parameter 2 E stage $end
$scope begin adder_level[0] $end
$var parameter 2 F idx $end
$upscope $end
$scope begin adder_level[1] $end
$var parameter 2 G idx $end
$upscope $end
$scope begin adder_level[2] $end
$var parameter 3 H idx $end
$upscope $end
$scope begin adder_level[3] $end
$var parameter 3 I idx $end
$upscope $end
$upscope $end
$scope begin adder_stages[2] $end
$var parameter 32 J STAGE_SIZE $end
$var parameter 3 K stage $end
$scope begin adder_level[0] $end
$var parameter 2 L idx $end
$upscope $end
$scope begin adder_level[1] $end
$var parameter 2 M idx $end
$upscope $end
$upscope $end
$scope begin adder_stages[3] $end
$var parameter 32 N STAGE_SIZE $end
$var parameter 3 O stage $end
$scope begin adder_level[0] $end
$var parameter 2 P idx $end
$upscope $end
$upscope $end
$scope begin first_stage_assign[0] $end
$var parameter 2 Q idx $end
$upscope $end
$scope begin first_stage_assign[1] $end
$var parameter 2 R idx $end
$upscope $end
$scope begin first_stage_assign[2] $end
$var parameter 3 S idx $end
$upscope $end
$scope begin first_stage_assign[3] $end
$var parameter 3 T idx $end
$upscope $end
$scope begin first_stage_assign[4] $end
$var parameter 4 U idx $end
$upscope $end
$scope begin first_stage_assign[5] $end
$var parameter 4 V idx $end
$upscope $end
$scope begin first_stage_assign[6] $end
$var parameter 4 W idx $end
$upscope $end
$scope begin first_stage_assign[7] $end
$var parameter 4 X idx $end
$upscope $end
$upscope $end
$upscope $end
$enddefinitions $end
$comment Show the parameter values. $end
$dumpall
b111 X
b110 W
b101 V
b100 U
b11 T
b10 S
b1 R
b0 Q
b0 P
b11 O
b1 N
b1 M
b0 L
b10 K
b10 J
b11 I
b10 H
b1 G
b0 F
b1 E
b100 D
b1111 @
b10110 ?
b11 >
b10000 =
b111111111111111 <
b11111111111111111111111111111111000000000000000 ;
b1000 :
b10000 9
b10000 8
b110 7
b100100 6
b111 %
b10000 $
b1001 #
$end
#0
$dumpvars
bx C
bx B
bx A
bx 5
b0 4
bx 3
b10000 2
bx 1
bx 0
b0 /
b0 .
b0 -
b0 ,
1+
b0 *
1)
0(
bx '
bx &
bx "
bx !
$end
#5000
b0 "
b0 5
b0 1
b0 &
b0 3
b0 A
b0 !
b0 B
b0 0
b0 '
b10000 C
b10000 2
1(
#10000
0(
#15000
b111 2
b1000 C
1(
#20000
0(
b1 .
0+
#25000
b100000000000000 A
b100000000000000 0
b1 ,
b1 '
b10000 C
b10000 2
b100000000000000 /
b100000000000000 4
1(
#30000
0(
#35000
b100000 "
b100000 1
b100000000000000000000 &
b10 '
b10 ,
b0 /
b0 4
b10000 2
b1000 C
1(
#40000
0(
#45000
b1100000 "
b1100000 1
b1100000000000000000000 &
b0 A
b0 0
b11 ,
b11 '
b10000 C
b10000 2
1(
#50000
0(
#55000
b11000000 "
b11000000 1
b11000000000000000000000 &
b100 '
b100 ,
b10000 2
b1000 C
1(
#60000
0(
#65000
b110000000 "
b110000000 1
b110000000000000000000000 &
b101 ,
b101 '
b10000 C
b10000 2
1(
#70000
0(
#75000
b1100000000 "
b1100000000 1
b1100000000000000000000000 &
b110 '
b110 ,
b10000 2
b1000 C
1(
#80000
0(
#85000
b11000000000 "
b11000000000 1
b11000000000000000000000000 &
b111 ,
b111 '
b10000 C
b10000 2
1(
#90000
0(
#95000
b110000000000 "
b110000000000 1
b100000 5
b110000000000000000000000000 &
b1000 '
b1000 ,
b100000000000000000000 3
b10000 2
b1000 C
1(
#100000
0(
#105000
b1100000000000 "
b1100000 5
b1100000000000 1
b1100000000000000000000000000 &
b1100000000000000000000 3
b100000 !
b100000 B
b1001 ,
b1001 '
b10000 C
b10000 2
1(
#110000
0(
#115000
b10000000000000 "
b10000000000000 1
b11000000 5
b10000000000000000000000000000 &
b1010 '
b1010 ,
b1100000 !
b1100000 B
b11000000000000000000000 3
b10000 2
b1000 C
1(
#120000
0(
#125000
b1100000000000 "
b110000000 5
b1100000000000 1
b1100000000000000000000000000 &
b110000000000000000000000 3
b11000000 !
b11000000 B
b1011 ,
b1011 '
b10000 C
b10000 2
1(
#130000
0(
#135000
b110000000000 "
b110000000000 1
b1100000000 5
b110000000000000000000000000 &
b1100 ,
b110000000 !
b110000000 B
b1100000000000000000000000 3
b10000 2
b1000 C
1(
#140000
0(
#145000
b11000000000 "
b11000000000 5
b11000000000 1
b11000000000000000000000000 &
b11000000000000000000000000 3
b1100000000 !
b1100000000 B
b1101 ,
b10000 C
b10000 2
1(
#150000
0(
#155000
b1100000000 "
b1100000000 1
b110000000000 5
b1100000000000000000000000 &
b1110 ,
b11000000000 !
b11000000000 B
b110000000000000000000000000 3
b10000 2
b1000 C
1(
#160000
0(
#165000
b110000000 "
b1100000000000 5
b110000000 1
b110000000000000000000000 &
b1100000000000000000000000000 3
b110000000000 !
b110000000000 B
b1111 ,
b10000 C
b10000 2
1(
#170000
0(
#175000
b11000000 "
b11000000 1
b10000000000000 5
b11000000000000000000000 &
b10000 ,
b1100000000000 !
b1100000000000 B
b10000000000000000000000000000 3
b10000 2
b1000 C
1(
#180000
0(
#185000
b1100000 "
b1100000000000 5
b1100000 1
b1100000000000000000000 &
b1100000000000000000000000000 3
b10000000000000 !
b10000000000000 B
b10001 ,
b10000 C
b10000 2
1(
#190000
0(
#195000
b100000 "
b100000 1
b110000000000 5
b100000000000000000000 &
b10010 ,
b1100000000000 !
b1100000000000 B
b110000000000000000000000000 3
b10000 2
b1000 C
1(
#200000
0(
#205000
b0 "
b11000000000 5
b0 1
b0 &
b11000000000000000000000000 3
b110000000000 !
b110000000000 B
b10011 ,
b10000 C
b10000 2
1(
#210000
0(
#215000
b1100000000 5
b10100 ,
b11000000000 !
b11000000000 B
b1100000000000000000000000 3
b111 2
b1000 C
1(
#220000
0(
#225000
b110000000 5
b110000000000000000000000 3
b1100000000 !
b1100000000 B
b10101 ,
b10000 C
b10000 2
1(
#230000
0(
#235000
b11000000 5
b10110 ,
b110000000 !
b110000000 B
b11000000000000000000000 3
b10 .
b111 2
b1000 C
1(
#240000
0(
#245000
b1100000 5
b1100000000000000000000 3
b10000000000000 A
b11000000 !
b11000000 B
b10000000000000 0
b10111 ,
b10000 C
b10000 2
b10000000000000 /
b10000000000000 4
1(
#250000
0(
#255000
b10000 "
b10000 1
b100000 5
b10000000000000000000 &
b11000 ,
b1100000 !
b1100000 B
b100000000000000000000 3
b10000 2
b1000 C
1(
#260000
0(
#265000
b110000 "
b0 5
b110000 1
b110000000000000000000 &
b0 3
b100000 !
b100000 B
b11001 ,
b10000 C
b10000 2
1(
#270000
0(
#275000
b1110000 "
b1110000 1
b1110000000000000000000 &
b11010 ,
b0 !
b0 B
b10000 2
b1000 C
1(
#280000
0(
#285000
b11110000 "
b11110000 1
b11110000000000000000000 &
b11011 ,
b10000 C
b10000 2
1(
#290000
0(
#295000
b111110000 "
b111110000 1
b111110000000000000000000 &
b11100 ,
b10000 2
b1000 C
1(
#300000
0(
#305000
b1111110000 "
b1111110000 1
b1111110000000000000000000 &
b11101 ,
b10000 C
b10000 2
1(
#310000
0(
#315000
b11111110000 "
b11111110000 1
b10000 5
b11111110000000000000000000 &
b11110 ,
b10000000000000000000 3
b10000 2
b1000 C
1(
#320000
0(
#325000
b111111110000 "
b110000 5
b111111110000 1
b111111110000000000000000000 &
b110000000000000000000 3
b10000 !
b10000 B
b11111 ,
b10000 C
b10000 2
1(
#330000
0(
#335000
b1011111110000 "
b1011111110000 1
b1110000 5
b1011111110000000000000000000 &
b100000 ,
b110000 !
b110000 B
b1110000000000000000000 3
b10000 2
b1000 C
1(
#340000
0(
#345000
b1101111110000 "
b11110000 5
b1101111110000 1
b1101111110000000000000000000 &
b11110000000000000000000 3
b1110000 !
b1110000 B
b100001 ,
b10000 C
b10000 2
1(
#350000
0(
#355000
b1110111110000 "
b1110111110000 1
b111110000 5
b1110111110000000000000000000 &
b100010 ,
b11110000 !
b11110000 B
b111110000000000000000000 3
b10000 2
b1000 C
1(
#360000
0(
#365000
b1111011110000 "
b1111110000 5
b1111011110000 1
b1111011110000000000000000000 &
b1111110000000000000000000 3
b111110000 !
b111110000 B
b100011 ,
b10000 C
b10000 2
1(
#370000
0(
#375000
b1111101110000 "
b1111101110000 1
b11111110000 5
b1111101110000000000000000000 &
b100100 ,
b1111110000 !
b1111110000 B
b11111110000000000000000000 3
b10000 2
b1000 C
1(
#380000
0(
#385000
b1111110110000 "
b111111110000 5
b1111110110000 1
b1111110110000000000000000000 &
b111111110000000000000000000 3
b11111110000 !
b11111110000 B
b100101 ,
b10000 C
b10000 2
1(
#390000
0(
#395000
b1111111010000 "
b1111111010000 1
b1011111110000 5
b1111111010000000000000000000 &
b100110 ,
b111111110000 !
b111111110000 B
b1011111110000000000000000000 3
b10000 2
b1000 C
1(
#400000
0(
#405000
b1111111100000 "
b1101111110000 5
b1111111100000 1
b1111111100000000000000000000 &
b1101111110000000000000000000 3
b1011111110000 !
b1011111110000 B
b100111 ,
b10000 C
b10000 2
1(
#410000
0(
#415000
b1110111110000 5
b101000 ,
b1101111110000 !
b1101111110000 B
b1110111110000000000000000000 3
b111 2
b1000 C
1(
#420000
0(
#425000
b1111011110000 5
b1111011110000000000000000000 3
b1110111110000 !
b1110111110000 B
b101001 ,
b10000 C
b10000 2
1(
#430000
0(
#435000
b1111101110000 5
b101010 ,
b1111011110000 !
b1111011110000 B
b1111101110000000000000000000 3
b111 2
b1000 C
1(
#440000
0(
#445000
b1111110110000 5
b1111110110000000000000000000 3
b1111101110000 !
b1111101110000 B
b101011 ,
b10000 C
b10000 2
1(
#450000
0(
#455000
b1111111010000 5
b101100 ,
b1111110110000 !
b1111110110000 B
b1111111010000000000000000000 3
b111 2
b1000 C
1(
#460000
0(
#465000
b1111111100000 5
b1111111100000000000000000000 3
b1111111010000 !
b1111111010000 B
b101101 ,
b10000 C
b10000 2
1(
#470000
0(
#475000
b101110 ,
b1111111100000 !
b1111111100000 B
b111 2
b1000 C
1(
#480000
0(
#485000
b101111 ,
b10000 C
b10000 2
1(
#490000
0(
#495000
b110000 ,
b111 2
b1000 C
1(
#500000
0(
#505000
b110001 ,
b10000 C
b10000 2
1(
#510000
0(
#515000
b110010 ,
b111 2
b1000 C
1(
#520000
0(
#525000
b110011 ,
b10000 C
b10000 2
1(
#530000
0(
#535000
b110100 ,
b111 2
b1000 C
1(
#540000
0(
#545000
b0 A
b0 0
b110101 ,
b10000 C
b10000 2
b0 /
b0 4
1(
#550000
0(
#555000
b1111111010000 "
b1111111010000 1
b1111111010000000000000000000 &
b110110 ,
b10000 2
b1000 C
1(
#560000
0(
#565000
b1111110110000 "
b1111110110000 1
b1111110110000000000000000000 &
b110111 ,
b10000 C
b10000 2
1(
#570000
0(
#575000
b1111101110000 "
b1111101110000 1
b1111101110000000000000000000 &
b111000 ,
b10000 2
b1000 C
1(
#580000
0(
#585000
b1111011110000 "
b1111011110000 1
b1111011110000000000000000000 &
b111001 ,
b10000 C
b10000 2
1(
#590000
0(
#595000
b1110111110000 "
b1110111110000 1
b1110111110000000000000000000 &
b111010 ,
b10000 2
b1000 C
1(
#600000
0(
#605000
b1101111110000 "
b1101111110000 1
b1101111110000000000000000000 &
b111011 ,
b10000 C
b10000 2
1(
#610000
0(
#615000
b1011111110000 "
b1011111110000 1
b1111111010000 5
b1011111110000000000000000000 &
b111100 ,
b1111111010000000000000000000 3
b10000 2
b1000 C
1(
#620000
0(
#625000
b111111110000 "
b1111110110000 5
b111111110000 1
b111111110000000000000000000 &
b1111110110000000000000000000 3
b1111111010000 !
b1111111010000 B
b111101 ,
b10000 C
b10000 2
1(
#630000
0(
#635000
b11111110000 "
b11111110000 1
b1111101110000 5
b11111110000000000000000000 &
b111110 ,
b1111110110000 !
b1111110110000 B
b1111101110000000000000000000 3
b10000 2
b1000 C
1(
#640000
0(
#645000
b1111110000 "
b1111011110000 5
b1111110000 1
b1111110000000000000000000 &
b1111011110000000000000000000 3
b1111101110000 !
b1111101110000 B
b111111 ,
b10000 C
b10000 2
1(
#650000
0(
#655000
b111110000 "
b111110000 1
b1110111110000 5
b111110000000000000000000 &
b1000000 ,
b1111011110000 !
b1111011110000 B
b1110111110000000000000000000 3
b10000 2
b1000 C
1(
#660000
0(
#665000
b11110000 "
b1101111110000 5
b11110000 1
b11110000000000000000000 &
b1101111110000000000000000000 3
b1110111110000 !
b1110111110000 B
b1000001 ,
b10000 C
b10000 2
1(
#670000
0(
#675000
b1110000 "
b1110000 1
b1011111110000 5
b1110000000000000000000 &
b1000010 ,
b1101111110000 !
b1101111110000 B
b1011111110000000000000000000 3
b10000 2
b1000 C
1(
#680000
0(
#685000
b110000 "
b111111110000 5
b110000 1
b110000000000000000000 &
b111111110000000000000000000 3
b1011111110000 !
b1011111110000 B
b1000011 ,
b10000 C
b10000 2
1(
#690000
0(
#695000
b10000 "
b10000 1
b11111110000 5
b10000000000000000000 &
b1000100 ,
b111111110000 !
b111111110000 B
b11111110000000000000000000 3
b10000 2
b1000 C
1(
#700000
0(
#705000
b0 "
b1111110000 5
b0 1
b0 &
b1111110000000000000000000 3
b11111110000 !
b11111110000 B
b1000101 ,
b10000 C
b10000 2
1(
#710000
0(
#715000
b111110000 5
b1000110 ,
b1111110000 !
b1111110000 B
b111110000000000000000000 3
b111 2
b1000 C
1(
#720000
0(
#725000
b11110000 5
b11110000000000000000000 3
b111110000 !
b111110000 B
b1000111 ,
b10000 C
b10000 2
1(
#730000
0(
#735000
b1110000 5
b1001000 ,
b11110000 !
b11110000 B
b1110000000000000000000 3
b111 2
b1000 C
1(
#740000
0(
#745000
b110000 5
b110000000000000000000 3
b1110000 !
b1110000 B
b1001001 ,
b10000 C
b10000 2
b11 .
1(
#750000
0(
#755000
b10000 5
b1001010 ,
b110000 !
b110000 B
b10000000000000000000 3
b111111111111111 /
b111111111111111 4
b111 2
b1000 C
1(
#760000
0(
#765000
b0 5
b0 3
b111111111111111 A
b10000 !
b10000 B
b111111111111111 0
b1001011 ,
b10000 C
b10000 2
1(
#770000
0(
#775000
b1000000 "
b1000000 1
b111111111111111000000 &
b1001100 ,
b0 !
b0 B
b10000 2
b1000 C
1(
#780000
0(
#785000
b11000000 "
b11000000 1
b10111111111111101000000 &
b1001101 ,
b10000 C
b10000 2
1(
#790000
0(
#795000
b111000000 "
b111000000 1
b110111111111111001000000 &
b1001110 ,
b10000 2
b1000 C
1(
#800000
0(
#805000
b1111000000 "
b1111000000 1
b1110111111111110001000000 &
b1001111 ,
b10000 C
b10000 2
1(
#810000
0(
#815000
b11111000000 "
b11111000000 1
b11110111111111100001000000 &
b1010000 ,
b10000 2
b1000 C
1(
#820000
0(
#825000
b111111000000 "
b111111000000 1
b111110111111111000001000000 &
b1010001 ,
b10000 C
b10000 2
1(
#830000
0(
#835000
b1111111000000 "
b1111111000000 1
b1000000 5
b1111110111111110000001000000 &
b1010010 ,
b111111111111111000000 3
b10000 2
b1000 C
1(
#840000
0(
#845000
b11111111000000 "
b11000000 5
b11111111000000 1
b11111110111111100000001000000 &
b10111111111111101000000 3
b1000000 !
b1000000 B
b1010011 ,
b10000 C
b10000 2
1(
#850000
0(
#855000
b101111110111111 "
b101111110111111 1
b111000000 5
b101111110111111010000001000000 &
b1010100 ,
b11000000 !
b11000000 B
b110111111111111001000000 3
b10000 2
b1000 C
1(
#860000
0(
#865000
b110111110111111 "
b1111000000 5
b110111110111111 1
b110111110111111001000001000000 &
b1110111111111110001000000 3
b111000000 !
b111000000 B
b1010101 ,
b10000 C
b10000 2
1(
#870000
0(
#875000
b111011110111111 "
b111011110111111 1
b11111000000 5
b111011110111111000100001000000 &
b1010110 ,
b1111000000 !
b1111000000 B
b11110111111111100001000000 3
b10000 2
b1000 C
1(
#880000
0(
#885000
b111101110111111 "
b111111000000 5
b111101110111111 1
b111101110111111000010001000000 &
b111110111111111000001000000 3
b11111000000 !
b11111000000 B
b1010111 ,
b10000 C
b10000 2
1(
#890000
0(
#895000
b111110110111111 "
b111110110111111 1
b1111111000000 5
b111110110111111000001001000000 &
b1011000 ,
b111111000000 !
b111111000000 B
b1111110111111110000001000000 3
b10000 2
b1000 C
1(
#900000
0(
#905000
b111111010111111 "
b11111111000000 5
b111111010111111 1
b111111010111111000000101000000 &
b11111110111111100000001000000 3
b1111111000000 !
b1111111000000 B
b1011001 ,
b10000 C
b10000 2
1(
#910000
0(
#915000
b111111100111111 "
b111111100111111 1
b101111110111111 5
b111111100111111000000011000000 &
b1011010 ,
b11111111000000 !
b11111111000000 B
b101111110111111010000001000000 3
b10000 2
b1000 C
1(
#920000
0(
#925000
b111111101111111 "
b110111110111111 5
b111111101111111 1
b111111101111111000000010000000 &
b110111110111111001000001000000 3
b101111110111111 !
b101111110111111 B
b1011011 ,
b10000 C
b10000 2
1(
#930000
0(
#935000
b111011110111111 5
b1011100 ,
b110111110111111 !
b110111110111111 B
b111011110111111000100001000000 3
b111 2
b1000 C
1(
#940000
0(
#945000
b111101110111111 5
b111101110111111000010001000000 3
b111011110111111 !
b111011110111111 B
b1011101 ,
b10000 C
b10000 2
1(
#950000
0(
#955000
b111110110111111 5
b1011110 ,
b111101110111111 !
b111101110111111 B
b111110110111111000001001000000 3
b0 /
b0 4
b111 2
b1000 C
1(
#960000
0(
#965000
b111111010111111 5
b111111010111111000000101000000 3
b0 A
b111110110111111 !
b111110110111111 B
b0 0
b1011111 ,
b10000 C
b10000 2
1(
#970000
0(
#975000
b111111100111111 "
b111111100111111 1
b111111100111111 5
b111111100111111000000011000000 &
b1100000 ,
b111111010111111 !
b111111010111111 B
b111111100111111000000011000000 3
b10000 2
b1000 C
1(
#980000
0(
#985000
b111111010111111 "
b111111101111111 5
b111111010111111 1
b111111010111111000000101000000 &
b111111101111111000000010000000 3
b111111100111111 !
b111111100111111 B
b1100001 ,
b10000 C
b10000 2
1(
#990000
0(
